restmon/__init__.py
restmon/client.py
restmon/log.py
restmon-1.2.0.dist-info/DESCRIPTION.rst
restmon-1.2.0.dist-info/METADATA
restmon-1.2.0.dist-info/RECORD
restmon-1.2.0.dist-info/WHEEL
restmon-1.2.0.dist-info/entry_points.txt
restmon-1.2.0.dist-info/metadata.json
restmon-1.2.0.dist-info/top_level.txt
