Metadata-Version: 2.0
Name: restmon
Version: 1.2.0
Summary: A monitoring tool to query REST API endpoints and log the result / latency
Home-page: https://github.com/kkirsche/restmon
Author: Kevin Kirsche
Author-email: kev.kirsche@gmail.com
License: BSD
Keywords: rest api monitor
Platform: UNKNOWN
Classifier: Development Status :: 3 - Alpha
Classifier: Intended Audience :: Developers
Classifier: Intended Audience :: System Administrators
Classifier: Topic :: System :: Monitoring
Classifier: License :: OSI Approved :: BSD License
Classifier: Programming Language :: Python :: 2
Classifier: Programming Language :: Python :: 2.7
Classifier: Programming Language :: Python :: 3
Classifier: Programming Language :: Python :: 3.3
Classifier: Programming Language :: Python :: 3.4
Classifier: Programming Language :: Python :: 3.5
Classifier: Programming Language :: Python :: 3.6
Requires-Dist: flatten-json
Requires-Dist: raven
Requires-Dist: requests
Provides-Extra: dev
Requires-Dist: pandoc; extra == 'dev'
Requires-Dist: pytest; extra == 'dev'
Provides-Extra: test
Requires-Dist: pytest; extra == 'test'
